sspanel/__init__.py
sspanel/__version__.py
sspanel/api.py
sspanel/control_panel.py
sspanel/exceptions.py
sspanel/help.py
sspanel/server_info.py
sspanel/urls.py
sspanel/utils.py
sspanel/certificate/survivalservers-com-chain.pem
sspanel/data/__init__.py
sspanel/data/survivalservers-com-chain.pem
sspanel-0.1.1.dist-info/LICENSE
sspanel-0.1.1.dist-info/METADATA
sspanel-0.1.1.dist-info/WHEEL
sspanel-0.1.1.dist-info/top_level.txt
sspanel-0.1.1.dist-info/zip-safe
sspanel-0.1.1.dist-info/RECORD
