Metadata-Version: 2.1
Name: sspanel
Version: 0.1.1
Summary: Simple API for the SurvivalServers.com Control Panel using HTTP requests.
Home-page: https://github.com/chr-ibb/sspanel
Author: Christopher Ibbotson
Author-email: me@chribbotson.com
License: MIT
Platform: UNKNOWN
Classifier: License :: OSI Approved :: MIT License
Classifier: Programming Language :: Python
Classifier: Programming Language :: Python :: 3
Classifier: Programming Language :: Python :: 3.7
Classifier: Programming Language :: Python :: 3.8
Classifier: Programming Language :: Python :: 3.9
Classifier: Programming Language :: Python :: Implementation :: CPython
Classifier: Programming Language :: Python :: Implementation :: PyPy
Requires-Python: >=3.7.0
Requires-Dist: requests (>=2.25.0)
